{
  "projects": {
      "someKey1": {
          "projectName": "project 1 name",
          "projectStatus": "finished",
          "projectStartDate": "25-08-2020",
          "projectDeadLine": "25-12-2020",
          "repositoryLink": "www.link.pl",
          "onlineAddrss": false,
          "projectAssumptions": [],
          "projectNotes": [
              "note1",
              "note2",
              "note3"
          ],
          "toDo": {
              "toDo 1": {
                  "isActive": true,
                  "status": "new",
                  "priority": "high",
                  "description": "toDo 1 description",
                  "toDoNote": [
                      "toDo 1 note 1",
                      "toDo 1 note 2",
                      "toDo 1 note 3"
                  ]
              }
          }
      },
      "someKey2": {
          "projectName": "project 2 name",
          "projectStatus": "planning",
          "projectStartDate": "25-08-2020",
          "projectDeadLine": "25-12-2020",
          "repositoryLink": "www.link.pl",
          "onlineAddrss": "",
          "projectAssumptions": [
              "note 1",
              "note 2",
              "note 3"
          ],
          "projectNotes": [
              "note1"
          ],
          "toDo": {}
      },
      "someKey3": {
          "projectName": "project 3 name",
          "projectStatus": "production",
          "projectStartDate": "25-08-2020",
          "projectDeadLine": "25-12-2020",
          "repositoryLink": "",
          "onlineAddrss": "www.online.pl",
          "projectAssumptions": [
              "note 1",
              "note 2",
              "note 3"
          ],
          "projectNotes": [
              "note1",
              "note2",
              "note3"
          ],
          "toDo": {
              "toDo 1": {
                  "isActive": true,
                  "status": "in progress",
                  "priority": "high",
                  "description": "toDo 1 description",
                  "toDoNote": [
                      "toDo 1 note 1",
                      "toDo 1 note 2",
                      "toDo 1 note 3"
                  ]
              },
              "toDo 2": {
                  "isActive": false,
                  "status": "rejected",
                  "priority": "low",
                  "description": "toDo 2 description",
                  "toDoNote": [
                      "toDo 2 note 1",
                      "toDo 2 note 2",
                      "toDo 2 note 3"
                  ]
              }
          }
      },
      "someKey4": {
          "projectName": "project 4 name",
          "projectStatus": "production",
          "projectStartDate": "25-08-2020",
          "projectDeadLine": "25-12-2020",
          "repositoryLink": "www.link.pl",
          "onlineAddrss": "www.online.pl",
          "projectAssumptions": [
              "note 1"
          ],
          "projectNotes": [
              "note1",
              "note2",
              "note3"
          ],
          "toDo": {
              "toDo 1": {
                  "isActive": true,
                  "status": "in progress",
                  "priority": "high",
                  "description": "toDo 2 description",
                  "toDoNote": [
                      "toDo 2 note 1",
                      "toDo 1 note 2",
                      "toDo 1 note 3"
                  ]
              },
              "toDo 2": {
                  "isActive": false,
                  "status": "rejected",
                  "priority": "low",
                  "description": "toDo 2 description",
                  "toDoNote": [
                      "toDo 2 note 1"
                  ]
              }
          }
      },
      "someKey5": {
          "projectName": "project 5 very very very very long name",
          "projectStatus": "production",
          "projectStartDate": "25-08-2020",
          "projectDeadLine": "25-12-2020",
          "repositoryLink": "www.link.pl",
          "onlineAddrss": "",
          "projectAssumptions": [
              "note 1"
          ],
          "projectNotes": [
              "note1",
              "note2",
              "note3"
          ],
          "toDo": {
              "toDo 1": {
                  "isActive": true,
                  "status": "in progress",
                  "priority": "high",
                  "description": "toDo 1 description",
                  "toDoNote": [
                      "toDo 1 note 1",
                      "toDo 1 note 2",
                      "toDo 1 note 3"
                  ]
              },
              "toDo 2": {
                  "isActive": false,
                  "status": "rejected",
                  "priority": "low",
                  "description": "toDo 2 description",
                  "toDoNote": [
                      "toDo 2 note 1"
                  ]
              }
          }
      }
  },
  "history": {
      "lastEdited": ""
  }
}